{
  "description": "Yoshi is a personal finance service that gives users access to linked financial accounts, transactions, investments, scores, and paper-trading workflows. Its product also supports AI-assistant access to that data through an MCP server.",
  "discoveredAt": "2026-07-02T22:44:07.179Z",
  "domain": "yoshi.ai",
  "summary": "Yoshi exposes a bearer-authenticated REST API at `https://api.yoshi.ai/v1`, a `yoshi` CLI, and a hosted MCP server at `https://agents.yoshi.ai/mcp`.",
  "surfaces": [
    {
      "authStatus": "required",
      "name": "Yoshi API",
      "slug": "yoshi-api",
      "type": "http",
      "url": "https://api.yoshi.ai/v1"
    },
    {
      "authStatus": "required",
      "name": "Yoshi MCP server",
      "slug": "yoshi-mcp-server",
      "type": "mcp",
      "url": "https://agents.yoshi.ai/mcp"
    },
    {
      "authStatus": "required",
      "command": "yoshi",
      "name": "Yoshi CLI",
      "packages": [
        {
          "identifier": "yoshi-ai-dev/yoshi-cli/yoshi",
          "registryType": "homebrew",
          "runtimeHint": "Homebrew"
        },
        {
          "identifier": "github.com/yoshi-ai-dev/yoshi-cli/cmd/yoshi",
          "registryType": "go",
          "runtimeHint": "Go 1.22+"
        }
      ],
      "slug": "yoshi-cli",
      "type": "cli"
    }
  ]
}
