{
  "domain": "graphql.myshopify.com",
  "summary": "Shopify exposes two GraphQL APIs (Admin and Storefront) plus a public UCP MCP endpoint; Admin requires a Shopify access token, Storefront accepts an access token or tokenless public access.",
  "surfaces": [
    {
      "authStatus": "required",
      "name": "Shopify GraphQL Admin API",
      "slug": "shopify-graphql-admin-api",
      "type": "graphql",
      "url": "https://{shop}.myshopify.com/admin/api/2026-07/graphql.json"
    },
    {
      "authStatus": "required",
      "name": "Shopify GraphQL Storefront API",
      "slug": "shopify-graphql-storefront-api",
      "type": "graphql",
      "url": "https://{shop}.myshopify.com/api/2026-07/graphql.json"
    },
    {
      "authStatus": "none",
      "name": "Shopify UCP MCP endpoint",
      "slug": "shopify-ucp-mcp-endpoint",
      "type": "mcp",
      "url": "https://graphql.myshopify.com/api/ucp/mcp"
    }
  ]
}
