{
  "description": "Polar is a merchant-of-record and billing platform for selling software, subscriptions, and digital products. It handles checkout, subscriptions, tax compliance, customer portal functions, and automated benefit delivery such as license keys and downloads.",
  "discoveredAt": "2026-07-02T20:45:42.144Z",
  "domain": "polar.sh",
  "summary": "Polar exposes a REST HTTP API with core and customer-portal surfaces plus remote MCP servers for production and sandbox; authentication is via organization bearer tokens, customer session bearer tokens, or OAuth 2.0/OpenID Connect access tokens depending on surface.",
  "surfaces": [
    {
      "authStatus": "required",
      "name": "Polar API",
      "slug": "polar-api",
      "type": "http",
      "url": "https://api.polar.sh/v1"
    },
    {
      "authStatus": "required",
      "name": "Polar Customer Portal API",
      "slug": "polar-customer-portal-api",
      "type": "http",
      "url": "https://api.polar.sh/v1/customer-portal"
    },
    {
      "authStatus": "required",
      "name": "Polar MCP Server (production)",
      "slug": "polar-mcp-server-production",
      "type": "mcp",
      "url": "https://mcp.polar.sh/mcp/polar-mcp"
    },
    {
      "authStatus": "required",
      "name": "Polar MCP Server (sandbox)",
      "slug": "polar-mcp-server-sandbox",
      "type": "mcp",
      "url": "https://mcp.polar.sh/mcp/polar-sandbox"
    }
  ]
}
