{
  "description": "dataatwork.org publishes an open skills and jobs dataset that relates job titles, descriptions, and skills. It provides programmatic access to this workforce data through the Open Skills API.",
  "discoveredAt": "2026-07-02T21:28:57.826Z",
  "domain": "dataatwork.org",
  "summary": "dataatwork.org exposes one public HTTP REST surface: the Open Skills API, documented by an OpenAPI/Swagger spec and requiring no authentication.",
  "surfaces": [
    {
      "authStatus": "none",
      "name": "Open Skills API",
      "slug": "open-skills-api",
      "spec": "https://api.apis.guru/v2/specs/dataatwork.org/1.0/swagger.json",
      "type": "http",
      "url": "http://api.dataatwork.org/v1"
    }
  ]
}
