{
  "description": "Grafana provides observability software and services for dashboards, metrics, logs, traces, profiling, alerting, and incident response, including managed Grafana Cloud and self-hosted Grafana. Its products let teams collect, query, visualize, and operate on telemetry and related operational data.",
  "discoveredAt": "2026-07-02T20:25:56.004Z",
  "domain": "grafana.com",
  "summary": "Grafana exposes two developer HTTP APIs—a tenant/instance Grafana HTTP API and the grafana.com Grafana Cloud API—and a Grafana MCP server; auth is via service account tokens, Cloud Access Policy tokens, or on-prem Basic auth for the instance HTTP API/MCP server.",
  "surfaces": [
    {
      "authStatus": "required",
      "name": "Grafana Cloud API (GCOM API)",
      "slug": "grafana-cloud-api-gcom-api",
      "type": "http",
      "url": "https://grafana.com/api"
    },
    {
      "authStatus": "required",
      "name": "Grafana HTTP API",
      "slug": "grafana-http-api",
      "type": "http",
      "url": "http://your.grafana.com"
    },
    {
      "authStatus": "required",
      "name": "Grafana MCP server",
      "slug": "grafana-mcp-server",
      "type": "mcp"
    }
  ]
}
