{
  "domain": "trimble.com",
  "summary": "Trimble exposes Trimble Connect developer surfaces: 6 authenticated HTTP APIs (Core, Core Account, Model, Organizer, Property Set, Topics) using Trimble Identity OAuth bearer tokens, plus a public Workspace API package for browser extensions/components.",
  "surfaces": [
    {
      "authStatus": "required",
      "name": "Trimble Connect Core API",
      "slug": "trimble-connect-core-api",
      "type": "http",
      "url": "https://app.connect.trimble.com/tc/api/2.0"
    },
    {
      "authStatus": "required",
      "name": "Trimble Connect Core Account API",
      "slug": "trimble-connect-core-account-api",
      "type": "http",
      "url": "https://ecom.connect.trimble.com/v1"
    },
    {
      "authStatus": "required",
      "name": "Trimble Connect Model API",
      "slug": "trimble-connect-model-api",
      "type": "http",
      "url": "https://api.connect.trimble.com"
    },
    {
      "authStatus": "required",
      "name": "Trimble Connect Organizer API",
      "slug": "trimble-connect-organizer-api",
      "type": "http"
    },
    {
      "authStatus": "required",
      "name": "Trimble Connect Property Set API",
      "slug": "trimble-connect-property-set-api",
      "type": "http"
    },
    {
      "authStatus": "required",
      "name": "Trimble Connect Topics API",
      "slug": "trimble-connect-topics-api",
      "type": "http"
    },
    {
      "authStatus": "none",
      "command": "trimble-connect-workspace-api",
      "name": "Trimble Connect Workspace API",
      "slug": "trimble-connect-workspace-api",
      "type": "cli"
    }
  ]
}
