{
  "domain": "uber.com",
  "summary": "Uber exposes the Riders REST API and Uber Eats Marketplace REST APIs; both use OAuth-based auth via Uber developer app credentials, with the Riders API also supporting legacy server tokens, and there is an external MCP server project for Uber rides whose auth could not be pinned from public docs.",
  "surfaces": [
    {
      "authStatus": "required",
      "name": "Uber Riders API",
      "slug": "uber-riders-api",
      "type": "http",
      "url": "https://api.uber.com/<version>"
    },
    {
      "authStatus": "required",
      "name": "Uber Eats Marketplace APIs Sandbox",
      "slug": "uber-eats-marketplace-apis-sandbox",
      "type": "http",
      "url": "https://sandbox-api.uber.com/<version>"
    },
    {
      "authStatus": "unknown",
      "name": "Uber MCP server",
      "slug": "uber-mcp-server",
      "type": "mcp"
    }
  ]
}
