{
  "description": "Hanko provides authentication and user management infrastructure, including passwordless/passkey flows, sessions, SSO, and user administration. It offers both a full authentication platform and a separate Passkey API for adding passkeys to an existing auth system.",
  "discoveredAt": "2026-07-02T20:28:17.233Z",
  "domain": "hanko.io",
  "summary": "Hanko exposes four documented HTTP API surfaces: a tenant-scoped Public API, Admin API, and Flow API for Hanko Auth, plus a tenant-scoped Passkey API on passkeys.hanko.io; no public GraphQL, MCP server, or CLI surface was found.",
  "surfaces": [
    {
      "authStatus": "required",
      "name": "Hanko Public API",
      "slug": "hanko-public-api",
      "type": "http",
      "url": "https://{tenant_id}.hanko.io"
    },
    {
      "authStatus": "required",
      "name": "Hanko Admin API",
      "slug": "hanko-admin-api",
      "type": "http",
      "url": "https://{tenant_id}.hanko.io/admin"
    },
    {
      "authStatus": "required",
      "name": "Hanko Passkey API",
      "slug": "hanko-passkey-api",
      "type": "http",
      "url": "https://passkeys.hanko.io/{tenant_id}"
    }
  ]
}
