{
  "description": "CyberArk provides identity security and privileged access products for managing identities, secrets, and secure access across cloud and hybrid environments. Its documentation spans SaaS platform services such as access management, secrets management, secure infrastructure access, and secure AI agent controls.",
  "discoveredAt": "2026-07-02T23:06:43.028Z",
  "domain": "cyberark.com",
  "summary": "CyberArk exposes a tenant-scoped Idira platform API catalog (mostly REST plus one documented GraphQL endpoint) authenticated with bearer tokens minted from an Identity service account, and it also documents a downloadable Secrets Manager MCP server without a public connect URL.",
  "surfaces": [
    {
      "authStatus": "required",
      "name": "CyberArk Idira platform APIs",
      "slug": "cyberark-idira-platform-apis",
      "type": "http"
    },
    {
      "authStatus": "required",
      "name": "Discovery & Context GraphQL API",
      "slug": "discovery-context-graphql-api",
      "spec": "introspection",
      "type": "graphql",
      "url": "https://<subdomain>.inventory.cyberark.cloud/api/graphql"
    },
    {
      "authStatus": "unknown",
      "name": "Secrets Manager MCP server",
      "slug": "secrets-manager-mcp-server",
      "type": "mcp"
    }
  ]
}
