{
  "description": "Google Business Profile APIs let organizations manage their business listing information on Google, including locations, attributes, categories, chains, and Google-updated location data. The `mybusinessbusinessinformation.googleapis.com` service is the Business Information API endpoint for that data.",
  "discoveredAt": "2026-07-02T23:46:24.355Z",
  "domain": "mybusinessbusinessinformation.googleapis.com",
  "summary": "1 HTTP API surface: the Google Business Profile Business Information REST API at `https://mybusinessbusinessinformation.googleapis.com/v1`, authenticated with Google OAuth 2.0 bearer tokens.",
  "surfaces": [
    {
      "authStatus": "required",
      "name": "Google Business Profile Business Information API",
      "slug": "google-business-profile-business-information-api",
      "type": "http",
      "url": "https://mybusinessbusinessinformation.googleapis.com/v1"
    }
  ]
}
