{
  "description": "Ragie is a managed retrieval-augmented generation platform for developers. It handles document ingestion, processing, indexing, retrieval, connectors, and related tooling for building AI applications over private data.",
  "discoveredAt": "2026-07-02T20:47:35.871Z",
  "domain": "ragie.ai",
  "summary": "Ragie exposes a bearer-authenticated REST API at https://api.ragie.ai, per-partition streamable-http MCP servers with undocumented connection URLs/auth details, and a `ragie` CLI authenticated via `RAGIE_API_KEY`.",
  "surfaces": [
    {
      "authStatus": "required",
      "name": "Ragie API",
      "slug": "ragie-api",
      "type": "http",
      "url": "https://api.ragie.ai"
    },
    {
      "authStatus": "unknown",
      "name": "Ragie MCP servers",
      "slug": "ragie-mcp-servers",
      "type": "mcp"
    },
    {
      "authStatus": "required",
      "command": "ragie",
      "name": "ragie CLI",
      "packages": [
        {
          "identifier": "ragieai/tap/ragie",
          "registryType": "homebrew"
        },
        {
          "identifier": "ragie",
          "registryType": "apt"
        },
        {
          "identifier": "ragieai/ragie-cli",
          "registryType": "github",
          "runtimeHint": "Go 1.16+"
        }
      ],
      "slug": "ragie-cli",
      "type": "cli"
    }
  ]
}
