{
  "domain": "quotes.rest",
  "summary": "quotes.rest exposes the They Said So Quotes REST API (OpenAPI YAML at quotes.rest/yaml/theysaidso.quotes.openapi.yaml?v5.1) with Bearer API-key auth; the quote-of-the-day routes are documented as public, but the site also says public access now requires an API token.",
  "surfaces": [
    {
      "authStatus": "required",
      "name": "They Said So Quotes API",
      "slug": "they-said-so-quotes-api",
      "spec": "https://quotes.rest/yaml/theysaidso.quotes.openapi.yaml?v5.1",
      "type": "http",
      "url": "https://quotes.rest"
    }
  ]
}
