{
  "domain": "proofx.co.uk",
  "summary": "ProofX exposes public verification plus authenticated web, Voice ID, and iOS app surfaces; no API/GraphQL/MCP/CLI docs were found on proofx.co.uk.",
  "surfaces": [
    {
      "authStatus": "required",
      "name": "ProofX web app",
      "slug": "proofx-web-app",
      "type": "http",
      "url": "https://proofx.co.uk"
    },
    {
      "authStatus": "none",
      "name": "ProofX content verification page",
      "slug": "proofx-content-verification-page",
      "type": "http",
      "url": "https://proofx.co.uk/verify"
    },
    {
      "authStatus": "required",
      "name": "ProofX Voice ID",
      "slug": "proofx-voice-id",
      "type": "http",
      "url": "https://proofx.co.uk/voice"
    },
    {
      "authStatus": "required",
      "name": "ProofX iOS app",
      "slug": "proofx-ios-app",
      "type": "http",
      "url": "https://proofx.co.uk/apps"
    }
  ]
}
