{
  "description": "Readwise is a reading and knowledge management service for saving, searching, and organizing highlights and Reader documents. It lets users work with their reading history across the original Readwise product and the Reader app.",
  "discoveredAt": "2026-07-02T22:22:56.714Z",
  "domain": "readwise.io",
  "summary": "Readwise exposes two token-authenticated HTTP APIs (Readwise API v2 and Reader API v3), an OAuth-authenticated remote MCP server at https://mcp2.readwise.io/mcp, and an npm-distributed `readwise` CLI that supports browser OAuth or direct access-token login.",
  "surfaces": [
    {
      "authStatus": "required",
      "name": "Readwise MCP Server",
      "slug": "readwise-mcp-server",
      "type": "mcp",
      "url": "https://mcp2.readwise.io/mcp"
    },
    {
      "authStatus": "required",
      "command": "readwise",
      "name": "Readwise CLI",
      "packages": [
        {
          "identifier": "@readwise/cli",
          "registryType": "npm",
          "runtimeHint": "node"
        }
      ],
      "slug": "readwise-cli",
      "type": "cli"
    },
    {
      "authStatus": "required",
      "name": "Readwise API",
      "slug": "readwise-api",
      "type": "http",
      "url": "https://readwise.io/api/v2"
    },
    {
      "authStatus": "required",
      "name": "Reader API",
      "slug": "reader-api",
      "type": "http",
      "url": "https://readwise.io/api/v3"
    }
  ]
}
