{
  "description": "Artue is an online marketplace for discovering and buying original artworks, with a focus on Korean and international contemporary artists. It also offers AI-assisted artwork search and a resale marketplace for collectors.",
  "discoveredAt": "2026-07-02T22:52:43.392Z",
  "domain": "artue.io",
  "summary": "Artue exposes an MCP server for AI agents at `https://artue.io/api/mcp`; no public developer docs or authentication details were found for any other API surface.",
  "surfaces": [
    {
      "authStatus": "unknown",
      "name": "Artue MCP Server",
      "slug": "artue-mcp-server",
      "type": "mcp",
      "url": "https://artue.io/api/mcp"
    }
  ]
}
