{
  "domain": "pyxl.pro",
  "summary": "Pyxl exposes one documented developer surface: an OAuth-protected MCP server at https://www.pyxl.pro/api/mcp using Pyxl OAuth (authorize/token/register endpoints) with scopes images:read, images:write, and user:read; no separate public HTTP, GraphQL, or CLI surface was confirmed.",
  "surfaces": [
    {
      "authStatus": "required",
      "name": "Pyxl MCP OAuth-protected surface",
      "slug": "pyxl-mcp-oauth-protected-surface",
      "type": "mcp",
      "url": "https://www.pyxl.pro/api/mcp"
    }
  ]
}
