{
  "description": "Jimdo is a website builder and online store platform for creating and managing websites. It also offers related tools such as domains, SEO features, and site analytics.",
  "discoveredAt": "2026-07-02T21:52:48.172Z",
  "domain": "jimdo.com",
  "summary": "Jimdo exposes a public OAuth-protected MCP server at https://website-creation-mcp.e.jimdo.com/mcp; no public HTTP/GraphQL API or CLI documentation was found on jimdo.com.",
  "surfaces": [
    {
      "authStatus": "required",
      "name": "Jimdo MCP server",
      "slug": "jimdo-mcp-server",
      "type": "mcp",
      "url": "https://website-creation-mcp.e.jimdo.com/mcp"
    }
  ]
}
