{
  "domain": "att.com",
  "summary": "AT&T exposes a public developer portal plus two programmatic surfaces found here: the OAuth token endpoint at `https://api.att.com/oauth/v4/token` and the SMS API at `https://api.att.com/sms/v3`, both authenticated with AT&T app credentials/OAuth Bearer tokens.",
  "surfaces": [
    {
      "authStatus": "required",
      "name": "AT&T OAuth 2.0 token service",
      "slug": "at-t-oauth-2-0-token-service",
      "type": "http",
      "url": "https://api.att.com/oauth/v4/token"
    },
    {
      "authStatus": "required",
      "name": "AT&T SMS API",
      "slug": "at-t-sms-api",
      "type": "http",
      "url": "https://api.att.com/sms/v3"
    }
  ]
}
