{
  "domain": "housecanary.com",
  "summary": "HouseCanary exposes two authenticated HTTP APIs (Analytics API and Order Manager API) using Basic auth with an API Key/Secret, plus an MCP server that reuses the same credentials via env vars.",
  "surfaces": [
    {
      "authStatus": "required",
      "name": "HouseCanary Analytics API",
      "slug": "housecanary-analytics-api",
      "type": "http",
      "url": "https://api.housecanary.com/v2"
    },
    {
      "authStatus": "required",
      "name": "HouseCanary Order Manager API",
      "slug": "housecanary-order-manager-api",
      "type": "http",
      "url": "https://order-manager-api.housecanary.com/client-api/v1"
    },
    {
      "authStatus": "required",
      "name": "HouseCanary MCP",
      "slug": "housecanary-mcp",
      "type": "mcp",
      "url": "https://housecanary.com/mcp"
    }
  ]
}
