{
  "description": "This domain is an Amazon S3 bucket endpoint used to host assets, including an OpenAPI document labeled EmailVerify in third-party API cataloging. No first-party developer site or additional public integration surfaces were found on this domain.",
  "discoveredAt": "2026-07-02T23:50:10.698Z",
  "domain": "paypi-default-images.s3.eu-west-1.amazonaws.com",
  "summary": "One detected HTTP API surface: an EmailVerify OpenAPI document hosted at `https://paypi-default-images.s3.eu-west-1.amazonaws.com/openapi.yaml`; authentication could not be confirmed from public evidence.",
  "surfaces": [
    {
      "authStatus": "unknown",
      "name": "EmailVerify API",
      "slug": "emailverify-api",
      "spec": "https://paypi-default-images.s3.eu-west-1.amazonaws.com/openapi.yaml",
      "type": "http"
    }
  ]
}
