{
  "description": "Google Cloud Build is a managed CI/CD service on Google Cloud for running builds, tests, and deployments. It integrates with source repositories and Google Cloud deployment targets to automate software delivery workflows.",
  "discoveredAt": "2026-07-02T23:01:58.546Z",
  "domain": "cloudbuild.googleapis.com",
  "summary": "Google Cloud Build exposes a REST API at `https://cloudbuild.googleapis.com` and a `gcloud builds` CLI surface; both use Google Cloud authentication via OAuth/ADC-backed bearer credentials.",
  "surfaces": [
    {
      "authStatus": "required",
      "name": "Cloud Build REST API",
      "slug": "cloud-build-rest-api",
      "type": "http",
      "url": "https://cloudbuild.googleapis.com"
    },
    {
      "authStatus": "required",
      "command": "gcloud",
      "name": "gcloud builds CLI",
      "packages": [
        {
          "identifier": "google-cloud-cli",
          "registryType": "generic"
        }
      ],
      "slug": "gcloud-builds-cli",
      "type": "cli"
    }
  ]
}
