{
  "domain": "redis.com",
  "summary": "Redis exposes two public HTTP APIs (Redis Cloud REST API and Redis Software REST API), plus the Redis MCP server and redisctl CLI; Cloud REST uses `x-api-key` + `x-api-secret-key`, Software REST uses HTTP Basic Auth.",
  "surfaces": [
    {
      "authStatus": "required",
      "name": "Redis Cloud REST API",
      "slug": "redis-cloud-rest-api",
      "type": "http",
      "url": "https://api.redislabs.com/v1"
    },
    {
      "authStatus": "required",
      "name": "Redis Software REST API",
      "slug": "redis-software-rest-api",
      "type": "http",
      "url": "https://localhost:9443/v1"
    },
    {
      "authStatus": "unknown",
      "name": "Redis MCP",
      "slug": "redis-mcp",
      "type": "mcp"
    },
    {
      "authStatus": "unknown",
      "command": "redisctl",
      "name": "redisctl",
      "slug": "redisctl",
      "type": "cli"
    }
  ]
}
