{
  "description": "Pigment is an enterprise business planning and performance management platform for modeling, forecasting, reporting, and analysis across finance, sales, HR, and operations. It centralizes governed business data and provides AI-assisted workflows, including MCP connectivity for external AI systems.",
  "discoveredAt": "2026-07-02T23:51:30.447Z",
  "domain": "pigment.com",
  "summary": "Pigment exposes a workspace-specific remote MCP server at `https://pigment.app/api/mcp/public/{id}` authenticated with Pigment account OAuth; no public REST, GraphQL, or standalone CLI surface was found on pigment.com subdomains.",
  "surfaces": [
    {
      "authStatus": "required",
      "name": "Pigment MCP Server",
      "slug": "pigment-mcp-server",
      "type": "mcp",
      "url": "https://pigment.app/api/mcp/public/{id}"
    }
  ]
}
