{
  "domain": "cdc.gov",
  "summary": "CDC exposes three developer surfaces: the public Content Services API, the authenticated NIO Autocoder API, and the authenticated MVPS Reports External API; no GraphQL, MCP, or CLI surfaces were found.",
  "surfaces": [
    {
      "authStatus": "none",
      "name": "CDC Content Services API",
      "slug": "cdc-content-services-api",
      "type": "http",
      "url": "https://tools.cdc.gov/api"
    },
    {
      "authStatus": "required",
      "name": "MVPS Reports External API",
      "slug": "mvps-reports-external-api",
      "type": "http",
      "url": "https://api.cdc.gov/mvps/1.0.0/"
    }
  ]
}
