{
  "domain": "stitchdata.com",
  "summary": "Stitch exposes two authenticated HTTP APIs (Connect API and Import API) plus public post-load webhooks; Connect uses a partner-issued Bearer token, and Import API uses a Stitch-generated Bearer access token.",
  "surfaces": [
    {
      "authStatus": "required",
      "name": "Stitch Connect API",
      "slug": "stitch-connect-api",
      "type": "http",
      "url": "https://api.stitchdata.com/v4"
    },
    {
      "authStatus": "required",
      "name": "Stitch Import API",
      "slug": "stitch-import-api",
      "type": "http",
      "url": "https://api.stitchdata.com"
    },
    {
      "authStatus": "none",
      "name": "Stitch post-load webhooks",
      "slug": "stitch-post-load-webhooks",
      "type": "http"
    }
  ]
}
