{
  "domain": "runzero.com",
  "summary": "runZero exposes one authenticated HTTP API, plus an MCP server and CLI whose auth mechanics could not be pinned from the pages read.",
  "surfaces": [
    {
      "authStatus": "required",
      "name": "runZero API",
      "slug": "runzero-api",
      "type": "http",
      "url": "https://console.runzero.com/api/v1.0"
    },
    {
      "authStatus": "unknown",
      "name": "runZero MCP server",
      "slug": "runzero-mcp-server",
      "type": "mcp"
    },
    {
      "authStatus": "unknown",
      "command": "runzero",
      "name": "runZero CLI",
      "slug": "runzero-cli",
      "type": "cli"
    }
  ]
}
