{
  "description": "Quo is a business phone and customer communication platform for calls, text messages, contacts, and related workflow data. It provides shared workspace access to conversations, users, calls, tasks, and integrations for businesses.",
  "discoveredAt": "2026-07-02T22:21:10.673Z",
  "domain": "quo.com",
  "summary": "Quo exposes two versioned REST API surfaces at https://api.quo.com authenticated by Quo-issued API keys, plus an official remote MCP server at https://mcp.quo.com/mcp using OAuth-based account connection.",
  "surfaces": [
    {
      "authStatus": "required",
      "name": "Quo API v1",
      "slug": "quo-api-v1",
      "type": "http",
      "url": "https://api.quo.com"
    },
    {
      "authStatus": "required",
      "name": "Quo MCP server",
      "slug": "quo-mcp-server",
      "type": "mcp",
      "url": "https://mcp.quo.com/mcp"
    }
  ]
}
