{
  "description": "Basecamp is a project management and team collaboration product from 37signals. Its product family includes multiple generations of Basecamp with separate APIs, along with an official CLI for terminal and AI-agent access.",
  "discoveredAt": "2026-07-02T22:54:52.147Z",
  "domain": "basecampapi.com",
  "summary": "Basecamp exposes three documented REST API surfaces—Basecamp 3, Basecamp 2, and Basecamp Classic—plus an official `basecamp` CLI; auth is via Launchpad OAuth for Basecamp 3 and optionally Basecamp 2/Classic, with Basic/API-token auth also supported on older APIs.",
  "surfaces": [
    {
      "authStatus": "required",
      "name": "Basecamp 2 REST API",
      "slug": "basecamp-2-rest-api",
      "type": "http",
      "url": "https://basecamp.com/{accountId}/api/v1"
    },
    {
      "authStatus": "required",
      "name": "Basecamp Classic REST API",
      "slug": "basecamp-classic-rest-api",
      "type": "http",
      "url": "https://{account-host}"
    },
    {
      "authStatus": "required",
      "command": "basecamp",
      "name": "Basecamp CLI",
      "packages": [
        {
          "identifier": "github.com/basecamp/basecamp-cli/cmd/basecamp",
          "registryType": "go",
          "runtimeHint": "go install"
        },
        {
          "identifier": "basecamp/basecamp-cli",
          "registryType": "github",
          "runtimeHint": "GitHub Releases"
        },
        {
          "identifier": "basecamp/tap/basecamp-cli",
          "registryType": "homebrew"
        }
      ],
      "slug": "basecamp-cli",
      "type": "cli"
    },
    {
      "authStatus": "required",
      "name": "Basecamp 3 REST API",
      "slug": "basecamp-3-rest-api",
      "type": "http",
      "url": "https://3.basecampapi.com/{accountId}"
    }
  ]
}
