{
  "domain": "uiic.co.in",
  "summary": "UIIC exposes one developer surface: an authenticated HTTP API on Apisetu (`https://apisetu.gov.in/uiic/v3`) with two endpoints, secured by API key + clientId.",
  "surfaces": [
    {
      "authStatus": "required",
      "name": "United India Insurance Company Limited API",
      "slug": "united-india-insurance-company-limited-api",
      "spec": "https://api.apis.guru/v2/specs/apisetu.gov.in/uiic/3.0.0/openapi.json",
      "type": "http",
      "url": "https://apisetu.gov.in/uiic/v3"
    }
  ]
}
