{
  "description": "Yoti provides identity and age assurance products, including document and biometric verification, facial age estimation, digital ID, trust and safety tooling, and eSignatures. Its products are used by businesses to verify users, assess age, and support related compliance and fraud-prevention workflows.",
  "discoveredAt": "2026-07-02T21:07:44.787Z",
  "domain": "yoti.com",
  "summary": "Yoti exposes multiple public HTTP APIs for identity verification, age verification, facial age estimation, trust/safety, and proof-of-age verification; no GraphQL, MCP server, or CLI surface was found in public docs.",
  "surfaces": [
    {
      "authStatus": "required",
      "name": "Yoti Identity Verification API",
      "slug": "yoti-identity-verification-api",
      "type": "http",
      "url": "https://api.yoti.com/idverify/v1"
    },
    {
      "authStatus": "required",
      "name": "Yoti Age Verification API",
      "slug": "yoti-age-verification-api",
      "type": "http"
    },
    {
      "authStatus": "required",
      "name": "Yoti Facial Age Estimation API",
      "slug": "yoti-facial-age-estimation-api",
      "type": "http",
      "url": "https://age.yoti.com"
    },
    {
      "authStatus": "required",
      "name": "Yoti Trust API",
      "slug": "yoti-trust-api",
      "type": "http",
      "url": "https://trust-and-safety.yoti.com"
    },
    {
      "authStatus": "required",
      "name": "Yoti Proof of Age API",
      "slug": "yoti-proof-of-age-api",
      "type": "http",
      "url": "https://api.yoti.com"
    }
  ]
}
