{
  "description": "This domain serves a Keycloak identity provider instance for authentication. The visible public pages are sign-in interfaces and OpenID Connect discovery metadata for the `master` realm.",
  "discoveredAt": "2026-07-02T23:51:31.782Z",
  "domain": "pdf-maker-keycloak-prod-swcyckruxq-uc.a.run.app",
  "summary": "No developer integration surfaces found for this domain; it appears to be a Keycloak login/identity host exposing OpenID Connect discovery metadata, but OAuth/OIDC endpoints are not recorded as developer surfaces.",
  "surfaces": []
}
