{
  "domain": "autoscout24.com",
  "summary": "AutoScout24 exposes one public developer integration surface: the Listing Creation REST API (OpenAPI spec at /assets/openapi/spec.yml) authenticated with account-based Basic Auth; no GraphQL, MCP, or CLI surface was confirmed.",
  "surfaces": [
    {
      "authStatus": "required",
      "name": "AutoScout24 Listing Creation API",
      "slug": "autoscout24-listing-creation-api",
      "spec": "https://listing-creation.api.autoscout24.com/assets/openapi/spec.yml",
      "type": "http",
      "url": "https://listing-creation.api.autoscout24.com"
    }
  ]
}
