{
  "description": "ACKO is an Indian digital insurance company offering products like car, bike, health, life, and travel insurance, along with enterprise insurance solutions for businesses. Its enterprise offering includes embedded insurance workflows such as policy issuance, retrieval, endorsements, and claims management.",
  "discoveredAt": "2026-07-02T21:09:48.743Z",
  "domain": "acko.com",
  "summary": "ACKO exposes a public MCP server at `https://atlas.live.acko.com/mcp` and an ACKO Enterprise HTTP API documented on its website; the Enterprise API’s authentication details and machine-readable spec were not publicly determinable from the accessible docs.",
  "surfaces": [
    {
      "authStatus": "none",
      "name": "ACKO MCP Server",
      "slug": "acko-mcp-server",
      "type": "mcp",
      "url": "https://atlas.live.acko.com/mcp"
    },
    {
      "authStatus": "unknown",
      "name": "ACKO Enterprise API",
      "slug": "acko-enterprise-api",
      "type": "http"
    }
  ]
}
