{
  "description": "Klaviyo is a B2C CRM and marketing automation platform for email, SMS, WhatsApp, customer data, and analytics. It helps businesses manage customer profiles, events, campaigns, flows, and related marketing operations.",
  "discoveredAt": "2026-07-02T20:31:58.281Z",
  "domain": "klaviyo.com",
  "summary": "Klaviyo exposes a versioned REST API at `https://a.klaviyo.com` with OpenAPI specs, plus a streamable-HTTP MCP server at `https://mcp.klaviyo.com/mcp?include-mcp-app=true`; auth uses private API keys, OAuth access tokens, and for specific client endpoints a public API key/site ID.",
  "surfaces": [
    {
      "authStatus": "required",
      "name": "Klaviyo MCP server",
      "slug": "klaviyo-mcp-server",
      "type": "mcp",
      "url": "https://mcp.klaviyo.com/mcp?include-mcp-app=true"
    },
    {
      "authStatus": "required",
      "name": "Klaviyo REST API",
      "slug": "klaviyo-rest-api",
      "spec": "https://raw.githubusercontent.com/klaviyo/openapi/main/openapi/stable/apis/get_accounts.json",
      "type": "http",
      "url": "https://a.klaviyo.com"
    }
  ]
}
