{
  "description": "Google Cloud On-Demand Scanning is a vulnerability scanning service for container images and packages within Artifact Analysis. It lets users trigger manual scans and retrieve scan results for supported artifacts.",
  "discoveredAt": "2026-07-02T23:50:20.575Z",
  "domain": "ondemandscanning.googleapis.com",
  "summary": "1 HTTP API surface: the Google Cloud On-Demand Scanning REST API at ondemandscanning.googleapis.com, authenticated with Google Cloud OAuth 2.0 bearer tokens/service-account credentials.",
  "surfaces": [
    {
      "authStatus": "required",
      "name": "Google Cloud On-Demand Scanning API",
      "slug": "google-cloud-on-demand-scanning-api",
      "type": "http",
      "url": "https://ondemandscanning.googleapis.com"
    }
  ]
}
