{
  "domain": "travelimpactmodel.googleapis.com",
  "summary": "Travel Impact Model exposes one authenticated HTTP/REST API and one public MCP server; the REST API uses a Google Cloud API key, and the MCP endpoint is unauthenticated per docs.",
  "surfaces": [
    {
      "authStatus": "required",
      "name": "Travel Impact Model API",
      "slug": "travel-impact-model-api",
      "type": "http",
      "url": "https://travelimpactmodel.googleapis.com"
    },
    {
      "authStatus": "none",
      "name": "Travel Impact Model MCP",
      "slug": "travel-impact-model-mcp",
      "type": "mcp",
      "url": "https://travelimpactmodel.googleapis.com/mcp"
    }
  ]
}
