{
  "domain": "blockscout.com",
  "summary": "Blockscout exposes a required-auth PRO HTTP API at https://api.blockscout.com/v2/api using the `apikey` query param with a PRO API key, a required-auth GraphQL API (e.g. `https://eth-sepolia.blockscout.com/api/v2/graphql`) using `Authorization: Bearer` with that key, a public MCP server at https://mcp.blockscout.com with no auth, and an Autoscout management API at https://autoscout.services.blockscout.com requiring an `x-api-key` from deploy.blockscout.com/api-keys.",
  "surfaces": [
    {
      "authStatus": "required",
      "name": "Blockscout PRO API",
      "slug": "blockscout-pro-api",
      "type": "http",
      "url": "https://api.blockscout.com/v2/api"
    },
    {
      "authStatus": "required",
      "name": "Blockscout GraphQL API",
      "slug": "blockscout-graphql-api",
      "spec": "introspection",
      "type": "graphql",
      "url": "https://eth-sepolia.blockscout.com/api/v2/graphql"
    },
    {
      "authStatus": "none",
      "name": "Blockscout MCP Server",
      "slug": "blockscout-mcp-server",
      "type": "mcp",
      "url": "https://mcp.blockscout.com"
    },
    {
      "authStatus": "required",
      "name": "Blockscout Autoscout API",
      "slug": "blockscout-autoscout-api",
      "type": "http",
      "url": "https://autoscout.services.blockscout.com"
    },
    {
      "authStatus": "unknown",
      "name": "Blockscout Smart Contract Verification API",
      "slug": "blockscout-smart-contract-verification-api",
      "type": "http"
    }
  ]
}
