{
  "description": "DrChrono provides cloud-based electronic health record, practice management, medical billing, and patient-engagement software for healthcare providers. Its platform includes partner integrations for accessing practice, scheduling, patient, billing, and clinical data.",
  "discoveredAt": "2026-07-02T21:36:08.065Z",
  "domain": "drchrono.com",
  "summary": "DrChrono exposes a documented OAuth-protected REST API for its EHR/practice-management platform; no public GraphQL API, MCP server, or CLI were found.",
  "surfaces": [
    {
      "authStatus": "required",
      "name": "DrChrono REST API v4",
      "slug": "drchrono-rest-api-v4",
      "type": "http",
      "url": "https://app.drchrono.com"
    }
  ]
}
