{
  "domain": "zoho.com",
  "summary": "Zoho CRM exposes an OAuth2-protected REST API v8, plus GraphQL, MCP, and ZDK CLI surfaces; only the REST API auth could be confirmed.",
  "surfaces": [
    {
      "authStatus": "required",
      "name": "Zoho CRM API v8",
      "slug": "zoho-crm-api-v8",
      "type": "http",
      "url": "https://www.zoho.com/crm/"
    },
    {
      "authStatus": "unknown",
      "name": "Zoho CRM GraphQL API",
      "slug": "zoho-crm-graphql-api",
      "type": "graphql",
      "url": "https://www.zoho.com/crm/"
    },
    {
      "authStatus": "unknown",
      "name": "Zoho CRM MCP",
      "slug": "zoho-crm-mcp",
      "type": "mcp",
      "url": "https://mcp.zoho.com"
    },
    {
      "authStatus": "unknown",
      "command": "zdk",
      "name": "Zoho ZDK CLI",
      "slug": "zoho-zdk-cli",
      "type": "cli"
    }
  ]
}
