{
  "description": "tableau.github.io is Tableau's GitHub Pages site for open-source project listings, samples, and links to developer documentation. It appears to be a documentation and project index rather than a programmatic service endpoint.",
  "discoveredAt": "2026-07-03T00:03:26.711Z",
  "domain": "tableau.github.io",
  "summary": "tableau.github.io is a public GitHub Pages landing site for Tableau open-source projects and documentation; no HTTP APIs, GraphQL APIs, MCP servers, or CLIs hosted on tableau.github.io were found.",
  "surfaces": []
}
