{
  "domain": "okteto.com",
  "summary": "Okteto exposes one documented HTTP API (Bearer Admin Access Token) and the `okteto` CLI (Personal Access Token via `okteto context use --token` or `OKTETO_TOKEN`); no GraphQL or MCP surface was found.",
  "surfaces": [
    {
      "authStatus": "required",
      "name": "Okteto API",
      "slug": "okteto-api",
      "type": "http",
      "url": "https://www.okteto.com/docs/admin/okteto-api/"
    },
    {
      "authStatus": "required",
      "command": "okteto",
      "name": "Okteto CLI",
      "slug": "okteto-cli",
      "type": "cli"
    }
  ]
}
